biomart/__init__.py
biomart/attribute.py
biomart/attribute_page.py
biomart/database.py
biomart/dataset.py
biomart/filter.py
biomart/server.py
biomart/lib/__init__.py
biomart/test/__init__.py
biomart/test/test_database.py
biomart/test/test_dataset.py
biomart/test/test_server.py
biomart-0.9.2.dist-info/DESCRIPTION.rst
biomart-0.9.2.dist-info/METADATA
biomart-0.9.2.dist-info/metadata.json
biomart-0.9.2.dist-info/RECORD
biomart-0.9.2.dist-info/top_level.txt
biomart-0.9.2.dist-info/WHEEL
