Metadata-Version: 1.1
Name: biomart
Version: 0.9.2
Summary: Python API that consumes the biomart webservice
Home-page: https://github.com/sebriois/biomart
Author: Sebastien Briois
Author-email: sebriois@gmail.com
License: BSD
Keywords: bioinformatics biomart
Platform: UNKNOWN
Classifier: Environment :: Web Environment
Classifier: Intended Audience :: Developers
Classifier: License :: OSI Approved :: BSD License
Classifier: Operating System :: OS Independent
Classifier: Programming Language :: Python
Classifier: Topic :: Scientific/Engineering :: Bio-Informatics
